Flask_Generic_Views-0.1.1.dist-info/DESCRIPTION.rst
Flask_Generic_Views-0.1.1.dist-info/METADATA
Flask_Generic_Views-0.1.1.dist-info/RECORD
Flask_Generic_Views-0.1.1.dist-info/WHEEL
Flask_Generic_Views-0.1.1.dist-info/metadata.json
Flask_Generic_Views-0.1.1.dist-info/top_level.txt
flask_generic_views/__init__.py
flask_generic_views/_compat.py
flask_generic_views/core.py
flask_generic_views/sqlalchemy.py
